dgsamples/__init__.py
dgsamples/_registerdata.py
dgsamples/_registerdata.py.bak
dgsamples/_version.py
dgsamples/__pycache__/__init__.cpython-36.pyc
dgsamples/__pycache__/_registerdata.cpython-36.pyc
dgsamples/__pycache__/_version.cpython-36.pyc
dgsamples/bayou_chip/extract_test.tif
dgsamples/bayou_chip/filename_map.PVL
dgsamples/bayou_chip/notes.txt
dgsamples/bayou_vectors/extract_test_line.dbf
dgsamples/bayou_vectors/extract_test_line.prj
dgsamples/bayou_vectors/extract_test_line.qpj
dgsamples/bayou_vectors/extract_test_line.shp
dgsamples/bayou_vectors/extract_test_line.shx
dgsamples/bayou_vectors/extract_test_point.dbf
dgsamples/bayou_vectors/extract_test_point.prj
dgsamples/bayou_vectors/extract_test_point.qpj
dgsamples/bayou_vectors/extract_test_point.shp
dgsamples/bayou_vectors/extract_test_point.shx
dgsamples/bayou_vectors/extract_test_poly.dbf
dgsamples/bayou_vectors/extract_test_poly.prj
dgsamples/bayou_vectors/extract_test_poly.qpj
dgsamples/bayou_vectors/extract_test_poly.shp
dgsamples/bayou_vectors/extract_test_poly.shx
dgsamples/bayou_vectors/filename_map.PVL
dgsamples/wv2_longmont_1k/filename_map.PVL
dgsamples/wv2_longmont_1k/053792616010_01_P001_MUL/14JUN20181517-M2AS-053792616010_01_P001-BROWSE.JPG
dgsamples/wv2_longmont_1k/053792616010_01_P001_MUL/14JUN20181517-M2AS-053792616010_01_P001.IMD
dgsamples/wv2_longmont_1k/053792616010_01_P001_MUL/14JUN20181517-M2AS-053792616010_01_P001.RPB
dgsamples/wv2_longmont_1k/053792616010_01_P001_MUL/14JUN20181517-M2AS-053792616010_01_P001.TIF
dgsamples/wv2_longmont_1k/053792616010_01_P001_MUL/14JUN20181517-M2AS-053792616010_01_P001.TIL
dgsamples/wv2_longmont_1k/053792616010_01_P001_MUL/14JUN20181517-M2AS-053792616010_01_P001.XML
dgsamples/wv2_longmont_1k/053792616010_01_P001_MUL/14JUN20181517-M2AS-053792616010_01_P001_README.TXT
dgsamples/wv2_longmont_1k/053792616010_01_P001_MUL/BASE.TXT
dgsamples-1.1.2.dist-info/METADATA
dgsamples-1.1.2.dist-info/RECORD
dgsamples-1.1.2.dist-info/WHEEL
dgsamples-1.1.2.dist-info/top_level.txt
