Metadata-Version: 2.1
Name: dgsamples
Version: 1.1.2
Summary: Sample image chips and vectors that can be used for unit testing
Home-page: UNKNOWN
Author: Nathan Longbotham
Author-email: longbotham@gmail.com
License: UNKNOWN
Platform: UNKNOWN
Requires-Dist: tinytools
